Metadata-Version: 2.1
Name: soundlit
Version: 0.1.0
Summary: The package contains a ready-to-use streamlit widget for downloading or recording audio. There is support for most audio formats.
Home-page: https://github.com/YeaMerci/streamlit-audio-widgets
Author: YeaMerci
Author-email: entertomerci@gmail.com
Keywords: waveform,converting,streamlit-audio-recorder,recorder,audio,streamlit,streamlit-component
Classifier: Programming Language :: Python :: 3
Classifier: License :: OSI Approved :: GNU General Public License v3 (GPLv3)
Classifier: Operating System :: OS Independent
Requires-Python: >=3.10
License-File: LICENSE.txt
Requires-Dist: altair==5.2.0
Requires-Dist: attrs==23.1.0
Requires-Dist: audioread==3.0.1
Requires-Dist: blinker==1.7.0
Requires-Dist: cachetools==5.3.2
Requires-Dist: certifi==2023.11.17
Requires-Dist: cffi==1.16.0
Requires-Dist: charset-normalizer==3.3.2
Requires-Dist: click==8.1.7
Requires-Dist: decorator==5.1.1
Requires-Dist: ffmpeg-python==0.2.0
Requires-Dist: future==0.18.3
Requires-Dist: gitdb==4.0.11
Requires-Dist: GitPython==3.1.40
Requires-Dist: idna==3.6
Requires-Dist: importlib-metadata==6.11.0
Requires-Dist: Jinja2==3.1.2
Requires-Dist: joblib==1.3.2
Requires-Dist: jsonschema==4.20.0
Requires-Dist: jsonschema-specifications==2023.11.2
Requires-Dist: lazy_loader==0.3
Requires-Dist: librosa==0.10.1
Requires-Dist: llvmlite==0.41.1
Requires-Dist: markdown-it-py==3.0.0
Requires-Dist: MarkupSafe==2.1.3
Requires-Dist: mdurl==0.1.2
Requires-Dist: msgpack==1.0.7
Requires-Dist: numba==0.58.1
Requires-Dist: numpy==1.26.2
Requires-Dist: packaging==23.2
Requires-Dist: pandas==2.1.4
Requires-Dist: Pillow==10.1.0
Requires-Dist: platformdirs==4.1.0
Requires-Dist: pooch==1.8.0
Requires-Dist: protobuf==4.25.1
Requires-Dist: pyarrow==14.0.1
Requires-Dist: pycparser==2.21
Requires-Dist: pydeck==0.8.1b0
Requires-Dist: Pygments==2.17.2
Requires-Dist: python-dateutil==2.8.2
Requires-Dist: pytz==2023.3.post1
Requires-Dist: referencing==0.32.0
Requires-Dist: requests==2.31.0
Requires-Dist: rich==13.7.0
Requires-Dist: rpds-py==0.13.2
Requires-Dist: scikit-learn==1.3.2
Requires-Dist: scipy==1.11.4
Requires-Dist: six==1.16.0
Requires-Dist: smmap==5.0.1
Requires-Dist: soundfile==0.12.1
Requires-Dist: soxr==0.3.7
Requires-Dist: streamlit==1.29.0
Requires-Dist: tenacity==8.2.3
Requires-Dist: threadpoolctl==3.2.0
Requires-Dist: toml==0.10.2
Requires-Dist: toolz==0.12.0
Requires-Dist: tornado==6.4
Requires-Dist: typing_extensions==4.9.0
Requires-Dist: tzdata==2023.3
Requires-Dist: tzlocal==5.2
Requires-Dist: urllib3==2.1.0
Requires-Dist: validators==0.22.0
Requires-Dist: watchdog==3.0.0
Requires-Dist: zipp==3.17.0
